tilpa_api_sdk/__init__.py
tilpa_api_sdk/adaptive_api.py
tilpa_api_sdk/example.py
tilpa_api_sdk/test.py
tilpa_api_sdk-0.0.1a0.dist-info/METADATA
tilpa_api_sdk-0.0.1a0.dist-info/WHEEL
tilpa_api_sdk-0.0.1a0.dist-info/licenses/LICENSE
tilpa_api_sdk-0.0.1a0.dist-info/RECORD
